PeptideConstructor/Geometry.py
PeptideConstructor/PCcli.py
PeptideConstructor/PeptideBuilder.py
PeptideConstructor/__init__.py
PeptideConstructor-0.2.1.dist-info/LICENSE.txt
PeptideConstructor-0.2.1.dist-info/METADATA
PeptideConstructor-0.2.1.dist-info/WHEEL
PeptideConstructor-0.2.1.dist-info/entry_points.txt
PeptideConstructor-0.2.1.dist-info/top_level.txt
PeptideConstructor-0.2.1.dist-info/RECORD
