Metadata-Version: 2.1
Name: PeptideConstructor
Version: 0.2.1
Summary: Create (DL-) peptide PDB files with specified secondary structures
Home-page: https://github.com/CharlesHahn/PeptideConstructor
Author: CharlesHahn
Author-email: 
License: UNKNOWN
Download-URL: https://github.com/CharlesHahn/PeptideConstructor/releases
Platform: cross-platform
Classifier: Development Status :: 4 - Beta
Classifier: License :: OSI Approved :: MIT License
Classifier: Programming Language :: Python
Classifier: Programming Language :: Python :: 3
Classifier: Topic :: Scientific/Engineering :: Bio-Informatics
Classifier: Topic :: Scientific/Engineering :: Chemistry
Classifier: Intended Audience :: Science/Research
Requires-Dist: Biopython
Requires-Dist: numpy
Provides-Extra: test
Requires-Dist: pytest ; extra == 'test'
Requires-Dist: coverage ; extra == 'test'
Requires-Dist: pytest-cov ; extra == 'test'
Requires-Dist: collective.checkdocs ; extra == 'test'
Requires-Dist: pygments ; extra == 'test'
Requires-Dist: Biopython ; extra == 'test'
Requires-Dist: numpy ; extra == 'test'
